{
  "project_info": {
    "project_number": "401570322799",
    "project_id": "gitdanu",
    "storage_bucket": "gitdanu.appspot.com"
  },
  "client": [
    {
      "client_info": {
        "mobilesdk_app_id": "1:401570322799:android:8b778f878f3aec4fb1b09a",
        "android_client_info": {
          "package_name": "com.example.kls_git"
        }
      },
      "oauth_client": [
        {
          "client_id": "401570322799-bn9pfsn3u0240e83v4g30piqj6n8pucs.apps.googleusercontent.com",
          "client_type": 3
        }
      ],
      "api_key": [
        {
          "current_key": "AIzaSyBwgr_KT4_acvBUvs2dK8G-he-3UbhCEh8"
        }
      ],
      "services": {
        "appinvite_service": {
          "other_platform_oauth_client": [
            {
              "client_id": "401570322799-bn9pfsn3u0240e83v4g30piqj6n8pucs.apps.googleusercontent.com",
              "client_type": 3
            }
          ]
        }
      }
    }
  ],
  "configuration_version": "1"
}